quick_logger/__init__.py
quick_logger/asynclog.py
quick_logger/core.py
quick_logger_colorful-0.3.7.dist-info/licenses/LICENSE
quick_logger_colorful-0.3.7.dist-info/METADATA
quick_logger_colorful-0.3.7.dist-info/WHEEL
quick_logger_colorful-0.3.7.dist-info/top_level.txt
quick_logger_colorful-0.3.7.dist-info/zip-safe
quick_logger_colorful-0.3.7.dist-info/RECORD
