Metadata-Version: 2.4
Name: quick-logger-colorful
Version: 0.3.7
Summary: A lightweight Python logging library with sync/async support, colorful terminal output, auto exception capture and zero configuration.
Home-page: https://github.com/huyuenshen/quick-logger.git
Author: huyuenshen
Author-email: huyuenshen@163.com
License: MIT
Classifier: Programming Language :: Python :: 3
Classifier: Programming Language :: Python :: 3.7
Classifier: Programming Language :: Python :: 3.8
Classifier: Programming Language :: Python :: 3.9
Classifier: Programming Language :: Python :: 3.10
Classifier: Programming Language :: Python :: 3.11
Classifier: Programming Language :: Python :: 3.12
Classifier: License :: OSI Approved :: MIT License
Classifier: Operating System :: OS Independent
Classifier: Intended Audience :: Developers
Classifier: Topic :: Software Development :: Libraries :: Python Modules
Classifier: Topic :: System :: Logging
Requires-Python: >=3.7
License-File: LICENSE
Dynamic: license-file
